typecode_libmagic/README.rst
typecode_libmagic/__init__.py
typecode_libmagic/build/bzip2/.BUILDINFO
typecode_libmagic/build/bzip2/.PKGINFO
typecode_libmagic/build/expat/.BUILDINFO
typecode_libmagic/build/expat/.PKGINFO
typecode_libmagic/build/file/.BUILDINFO
typecode_libmagic/build/file/.PKGINFO
typecode_libmagic/build/gcc-libs/.BUILDINFO
typecode_libmagic/build/gcc-libs/.PKGINFO
typecode_libmagic/build/gettext/.BUILDINFO
typecode_libmagic/build/gettext/.PKGINFO
typecode_libmagic/build/gmp/.BUILDINFO
typecode_libmagic/build/gmp/.PKGINFO
typecode_libmagic/build/libiconv/.BUILDINFO
typecode_libmagic/build/libiconv/.PKGINFO
typecode_libmagic/build/libsystre/.BUILDINFO
typecode_libmagic/build/libsystre/.PKGINFO
typecode_libmagic/build/libtre-git/.BUILDINFO
typecode_libmagic/build/libtre-git/.PKGINFO
typecode_libmagic/build/libwinpthread-git/.BUILDINFO
typecode_libmagic/build/libwinpthread-git/.PKGINFO
typecode_libmagic/build/mpc/.BUILDINFO
typecode_libmagic/build/mpc/.PKGINFO
typecode_libmagic/build/mpfr/.BUILDINFO
typecode_libmagic/build/mpfr/.PKGINFO
typecode_libmagic/build/xz/.BUILDINFO
typecode_libmagic/build/xz/.PKGINFO
typecode_libmagic/build/zlib/.BUILDINFO
typecode_libmagic/build/zlib/.PKGINFO
typecode_libmagic/data/magic.mgc
typecode_libmagic/lib/libasprintf-0.dll
typecode_libmagic/lib/libatomic-1.dll
typecode_libmagic/lib/libbz2-1.dll
typecode_libmagic/lib/libcharset-1.dll
typecode_libmagic/lib/libexpat-1.dll
typecode_libmagic/lib/libgcc_s_seh-1.dll
typecode_libmagic/lib/libgettextlib-0-19-8-1.dll
typecode_libmagic/lib/libgettextpo-0.dll
typecode_libmagic/lib/libgettextsrc-0-19-8-1.dll
typecode_libmagic/lib/libgmp-10.dll
typecode_libmagic/lib/libgmpxx-4.dll
typecode_libmagic/lib/libgomp-1.dll
typecode_libmagic/lib/libiconv-2.dll
typecode_libmagic/lib/libintl-8.dll
typecode_libmagic/lib/liblzma-5.dll
typecode_libmagic/lib/libmagic-1.dll
typecode_libmagic/lib/libquadmath-0.dll
typecode_libmagic/lib/libssp-0.dll
typecode_libmagic/lib/libstdc++-6.dll
typecode_libmagic-5.39.210531.dist-info/METADATA
typecode_libmagic-5.39.210531.dist-info/README.rst
typecode_libmagic-5.39.210531.dist-info/WHEEL
typecode_libmagic-5.39.210531.dist-info/bsd-new.LICENSE
typecode_libmagic-5.39.210531.dist-info/bsd-original.LICENSE
typecode_libmagic-5.39.210531.dist-info/bsd-simplified-darwin.LICENSE
typecode_libmagic-5.39.210531.dist-info/bsd-simplified.LICENSE
typecode_libmagic-5.39.210531.dist-info/entry_points.txt
typecode_libmagic-5.39.210531.dist-info/gpl-1.0-plus.LICENSE
typecode_libmagic-5.39.210531.dist-info/gpl-1.0.LICENSE
typecode_libmagic-5.39.210531.dist-info/isc.LICENSE
typecode_libmagic-5.39.210531.dist-info/libmagic.ABOUT
typecode_libmagic-5.39.210531.dist-info/libmagic.NOTICE
typecode_libmagic-5.39.210531.dist-info/public-domain.LICENSE
typecode_libmagic-5.39.210531.dist-info/top_level.txt
typecode_libmagic-5.39.210531.dist-info/typecode-libmagic.ABOUT
typecode_libmagic-5.39.210531.dist-info/RECORD
